shalat/__init__.py
shalat-0.1.0.dist-info/LICENSE
shalat-0.1.0.dist-info/METADATA
shalat-0.1.0.dist-info/WHEEL
shalat-0.1.0.dist-info/top_level.txt
shalat-0.1.0.dist-info/RECORD
